{
  "warnings": [
    "limit is higher than your plan allows"
  ],
  "meta": {
    "found": 49,
    "returned": 3,
    "limit": 3,
    "page": 1
  },
  "data": [
    {
      "uuid": "76602b3a-a3cd-497c-8dd1-8cfd1e477ac2",
      "title": "Agnellis in talks over Iveco sale, Tata Motors has made approach, sources say",
      "description": "Iveco in talks for possible sale, excluding defence business, with Tata Motors as potential buyer, shares rise.",
      "keywords": "",
      "snippet": "MILAN Italy's Agnelli family is in talks over the possible sale of truck maker Iveco, three sources told Reuters, with two mentioning Tata Motors as a potential...",
      "url": "https://www.thehindubusinessline.com/companies/agnellis-in-talks-over-iveco-sale-tata-motors-has-made-approach-sources-say/article69830803.ece",
      "image_url": "https://bl-i.thgim.com/public/incoming/ikk5p9/article69830820.ece/alternates/LANDSCAPE_1200/IMG_tata1_2_1_DPE9E03L.jpg",
      "language": "en",
      "published_at": "2025-07-19T08:07:12.000000Z",
      "source": "thehindubusinessline.com",
      "relevance_score": 40.28193,
      "entities": [
        {
          "symbol": "TATAMTRDVR-BL.NS",
          "name": "TATA MOTORS LTD.",
          "exchange": null,
          "exchange_long": null,
          "country": "in",
          "type": "equity",
          "industry": "N/A",
          "match_score": 35.914127,
          "sentiment_score": 0,
          "highlights": [
            {
              "highlight": ".\n\n($1 = 0.8590 euros)\n\nPublished on Jul[+74 characters]",
              "sentiment": 0,
              "highlighted_in": "main_text"
            }
          ]
        },
        {
          "symbol": "TTM.BA",
          "name": "TATA MOTORS LTD.",
          "exchange": null,
          "exchange_long": null,
          "country": "ar",
          "type": "equity",
          "industry": "Consumer Cyclical",
          "match_score": 35.91412,
          "sentiment_score": 0,
          "highlights": [
            {
              "highlight": ".\n\n($1 = 0.8590 euros)\n\nPublished on Jul[+74 characters]",
              "sentiment": 0,
              "highlighted_in": "main_text"
            }
          ]
        }
      ],
      "similar": []
    },
    {
      "uuid": "f28bc6ad-cd90-4135-ad0e-0434eb0f09b5",
      "title": "Tata Punch production crosses 6 lakh",
      "description": "Tata Punch hits 600,000 units, Range Rover Velar Autobiography trim, Jeep Trail Editions, and Volvo XC60 launch updates.",
      "keywords": "tata motors punch, range rover velar, jeep trail editions, volvo xc60",
      "snippet": "Tata Motors has announced the roll-out of the 600,000th unit of the Tata Punch, marking a record production achievement in under four years. Launched in October...",
      "url": "https://www.thehindubusinessline.com/specials/auto-focus/tata-punch-production-crosses-6-lakh/article69827124.ece",
      "image_url": "https://bl-i.thgim.com/public/incoming/79ucr4/article69827110.ece/alternates/LANDSCAPE_1200/News%20-%20Tata%20Punch.jpeg",
      "language": "en",
      "published_at": "2025-07-18T10:09:24.000000Z",
      "source": "thehindubusinessline.com",
      "relevance_score": 31.165455,
      "entities": [
        {
          "symbol": "TATAMTRDVR-BL.NS",
          "name": "TATA MOTORS LTD.",
          "exchange": null,
          "exchange_long": null,
          "country": "in",
          "type": "equity",
          "industry": "N/A",
          "match_score": 36.98238,
          "sentiment_score": 0,
          "highlights": [
            {
              "highlight": "© Motoring World\n\nPublished on July 18,[+69 characters]",
              "sentiment": 0,
              "highlighted_in": "main_text"
            }
          ]
        },
        {
          "symbol": "TTM.BA",
          "name": "TATA MOTORS LTD.",
          "exchange": null,
          "exchange_long": null,
          "country": "ar",
          "type": "equity",
          "industry": "Consumer Cyclical",
          "match_score": 36.98236,
          "sentiment_score": 0,
          "highlights": [
            {
              "highlight": "© Motoring World\n\nPublished on July 18,[+69 characters]",
              "sentiment": 0,
              "highlighted_in": "main_text"
            }
          ]
        }
      ],
      "similar": []
    },
    {
      "uuid": "8861665b-4d15-40b4-83ec-5f455c63801a",
      "title": "Top gainers & losers today 15th July 2025: Sensex, Nifty 50 recover, Auto stocks lead gains, HCL Tech, Tejas Networks, Rallis, Tata Tech react to Q1 show",
      "description": "Equity benchmark indices staged a mild recovery on Tuesday after falling for four trading sessions, boosted by dip in retail inflation, optimism on potential RBI rate cuts and steady foreign capital inflows.",
      "keywords": "sensex, RBI rate cut, nifty 50, HCL Tech",
      "snippet": "Equity benchmark indices staged a mild recovery on Tuesday after falling for four trading sessions, boosted by dip in retail inflation, optimism on potential RB...",
      "url": "https://www.thehindubusinessline.com/markets/stock-markets/top-gainers-losers-today-15th-july-2025-sensex-nifty-50-recover-auto-stocks-lead-gains-hcl-tech-tejas-networks-rallis-tata-tech-react-to-q1-show/article69814050.ece",
      "image_url": "https://bl-i.thgim.com/public/incoming/ba91k2/article69814068.ece/alternates/LANDSCAPE_1200/PO11_Chart.jpg",
      "language": "en",
      "published_at": "2025-07-15T07:51:13.000000Z",
      "source": "thehindubusinessline.com",
      "relevance_score": 24.63265,
      "entities": [
        {
          "symbol": "FRBA",
          "name": "First Bank",
          "exchange": null,
          "exchange_long": null,
          "country": "us",
          "type": "equity",
          "industry": "Financial Services",
          "match_score": 14.071671,
          "sentiment_score": 0.5719,
          "highlights": [
            {
              "highlight": "Ola Electric, Mankind Pharma, NMDC, IDFC[+303 characters]",
              "sentiment": 0.5719,
              "highlighted_in": "main_text"
            }
          ]
        },
        {
          "symbol": "^NSEI",
          "name": "Nifty 50",
          "exchange": null,
          "exchange_long": null,
          "country": "in",
          "type": "index",
          "industry": "N/A",
          "match_score": 55.110207,
          "sentiment_score": 0.329,
          "highlights": [
            {
              "highlight": "Sensex traded 399.34 pts or 0.49 per cen[+308 characters]",
              "sentiment": 0.7096,
              "highlighted_in": "main_text"
            },
            {
              "highlight": "Top gainers & losers today 15th July 2025: Sensex, <em>Nifty</em> <em>50</em> recover, Auto stocks lead gains, HCL Tech, Tejas Networks, Rallis, Tata Tech react to Q1 show",
              "sentiment": -0.0516,
              "highlighted_in": "title"
            }
          ]
        },
        {
          "symbol": "ASIANPAINT.BO",
          "name": "Asian Paints Limited",
          "exchange": null,
          "exchange_long": null,
          "country": "in",
          "type": "equity",
          "industry": "Basic Materials",
          "match_score": 23.732708,
          "sentiment_score": 0.4939,
          "highlights": [
            {
              "highlight": "Top gainers & losers intraday\n\nAmong the[+325 characters]",
              "sentiment": 0.4939,
              "highlighted_in": "main_text"
            }
          ]
        },
        {
          "symbol": "BAJAJ-AUTO.BO",
          "name": "Bajaj Auto Limited",
          "exchange": null,
          "exchange_long": null,
          "country": "in",
          "type": "equity",
          "industry": "Consumer Cyclical",
          "match_score": 22.366684,
          "sentiment_score": 0.4939,
          "highlights": [
            {
              "highlight": "Top gainers & losers intraday\n\nAmong the[+325 characters]",
              "sentiment": 0.4939,
              "highlighted_in": "main_text"
            }
          ]
        },
        {
          "symbol": "BIOCON.BO",
          "name": "Biocon Limited",
          "exchange": null,
          "exchange_long": null,
          "country": "in",
          "type": "equity",
          "industry": "Healthcare",
          "match_score": 37.77874,
          "sentiment_score": 0,
          "highlights": [
            {
              "highlight": "Midcap & smallcap movers\n\nIn the midcap [+261 characters]",
              "sentiment": 0,
              "highlighted_in": "main_text"
            }
          ]
        },
        {
          "symbol": "IDFCFIRSTB.BO",
          "name": "IDFC FIRST BANK LIMITED",
          "exchange": null,
          "exchange_long": null,
          "country": "in",
          "type": "equity",
          "industry": "N/A",
          "match_score": 26.32296,
          "sentiment_score": 0.5719,
          "highlights": [
            {
              "highlight": "Ola Electric, Mankind Pharma, NMDC, <em>[+312 characters]",
              "sentiment": 0.5719,
              "highlighted_in": "main_text"
            }
          ]
        },
        {
          "symbol": "BANDHANBNK.BO",
          "name": "Bandhan Bank Limited",
          "exchange": null,
          "exchange_long": null,
          "country": "in",
          "type": "equity",
          "industry": "N/A",
          "match_score": 23.80259,
          "sentiment_score": 0,
          "highlights": [
            {
              "highlight": "Midcap & smallcap movers\n\nIn the midcap [+261 characters]",
              "sentiment": 0,
              "highlighted_in": "main_text"
            }
          ]
        },
        {
          "symbol": "ESCORTS.BO",
          "name": "Escorts Limited",
          "exchange": null,
          "exchange_long": null,
          "country": "in",
          "type": "equity",
          "industry": "Industrials",
          "match_score": 19.831062,
          "sentiment_score": 0,
          "highlights": [
            {
              "highlight": "Midcap & smallcap movers\n\nIn the midcap [+252 characters]",
              "sentiment": 0,
              "highlighted_in": "main_text"
            }
          ]
        },
        {
          "symbol": "HEROMOTOCO.BO",
          "name": "Hero MotoCorp Limited",
          "exchange": null,
          "exchange_long": null,
          "country": "in",
          "type": "equity",
          "industry": "Consumer Cyclical",
          "match_score": 25.974892,
          "sentiment_score": -0.1027,
          "highlights": [
            {
              "highlight": "Top gainers & losers intraday\n\nAmong the[+325 characters]",
              "sentiment": -0.1027,
              "highlighted_in": "main_text"
            }
          ]
        },
        {
          "symbol": "TATASTEEL.BO",
          "name": "Tata Steel Limited",
          "exchange": null,
          "exchange_long": null,
          "country": "in",
          "type": "equity",
          "industry": "Basic Materials",
          "match_score": 22.839233,
          "sentiment_score": 0.4939,
          "highlights": [
            {
              "highlight": "Top gainers & losers intraday\n\nAmong the[+325 characters]",
              "sentiment": 0.4939,
              "highlighted_in": "main_text"
            }
          ]
        },
        {
          "symbol": "WIPRO.BO",
          "name": "Wipro Limited",
          "exchange": null,
          "exchange_long": null,
          "country": "in",
          "type": "equity",
          "industry": "Technology",
          "match_score": 18.482143,
          "sentiment_score": 0.4939,
          "highlights": [
            {
              "highlight": "Top gainers & losers intraday\n\nAmong the[+316 characters]",
              "sentiment": 0.4939,
              "highlighted_in": "main_text"
            }
          ]
        },
        {
          "symbol": "RPOWER.BO",
          "name": "Reliance Power Limited",
          "exchange": null,
          "exchange_long": null,
          "country": "in",
          "type": "equity",
          "industry": "Utilities",
          "match_score": 19.469185,
          "sentiment_score": 0.6482,
          "highlights": [
            {
              "highlight": "Tejas Networks, Inox Wind, Welspun Corp,[+288 characters]",
              "sentiment": 0.6482,
              "highlighted_in": "main_text"
            }
          ]
        },
        {
          "symbol": "CEATLTD.BO",
          "name": "CEAT Limited",
          "exchange": null,
          "exchange_long": null,
          "country": "in",
          "type": "equity",
          "industry": "Consumer Cyclical",
          "match_score": 21.692005,
          "sentiment_score": -0.296,
          "highlights": [
            {
              "highlight": "<em>CEAT</em>, Gillette, Force Motors, E[+270 characters]",
              "sentiment": -0.296,
              "highlighted_in": "main_text"
            }
          ]
        },
        {
          "symbol": "TEJASNET.BO",
          "name": "Tejas Networks Limited",
          "exchange": null,
          "exchange_long": null,
          "country": "in",
          "type": "equity",
          "industry": "Technology",
          "match_score": 49.373074,
          "sentiment_score": 0.301825,
          "highlights": [
            {
              "highlight": "Also read\n\nShares of HCL Tech, <em>Tejas[+246 characters]",
              "sentiment": 0.4939,
              "highlighted_in": "main_text"
            },
            {
              "highlight": "CEAT, Gillette, Force Motors, EID Parry,[+279 characters]",
              "sentiment": -0.296,
              "highlighted_in": "main_text"
            },
            {
              "highlight": "<em>Tejas</em> <em>Networks</em>, Inox W[+306 characters]",
              "sentiment": 0.6482,
              "highlighted_in": "main_text"
            },
            {
              "highlight": "Top gainers & losers today 15th July 2025: Sensex, Nifty 50 recover, Auto stocks lead gains, HCL Tech, <em>Tejas</em> <em>Networks</em>, Rallis, Tata Tech react to Q1 show",
              "sentiment": 0.3612,
              "highlighted_in": "title"
            }
          ]
        },
        {
          "symbol": "IDFC.BO",
          "name": "IDFC Limited",
          "exchange": null,
          "exchange_long": null,
          "country": "in",
          "type": "equity",
          "industry": "Financial Services",
          "match_score": 19.7859,
          "sentiment_score": 0.5719,
          "highlights": [
            {
              "highlight": "Ola Electric, Mankind Pharma, NMDC, <em>[+294 characters]",
              "sentiment": 0.5719,
              "highlighted_in": "main_text"
            }
          ]
        },
        {
          "symbol": "NMDC.BO",
          "name": "NMDC Limited",
          "exchange": null,
          "exchange_long": null,
          "country": "in",
          "type": "equity",
          "industry": "Basic Materials",
          "match_score": 20.471027,
          "sentiment_score": 0.5719,
          "highlights": [
            {
              "highlight": "Ola Electric, Mankind Pharma, <em>NMDC</[+294 characters]",
              "sentiment": 0.5719,
              "highlighted_in": "main_text"
            }
          ]
        },
        {
          "symbol": "ANANTRAJ.BO",
          "name": "Anant Raj Limited",
          "exchange": null,
          "exchange_long": null,
          "country": "in",
          "type": "equity",
          "industry": "Real Estate",
          "match_score": 26.73432,
          "sentiment_score": 0.5719,
          "highlights": [
            {
              "highlight": "Also read\n\nUnder the smallcap segment, <[+217 characters]",
              "sentiment": 0.5719,
              "highlighted_in": "main_text"
            }
          ]
        },
        {
          "symbol": "WELCORP.BO",
          "name": "Welspun Corp Limited",
          "exchange": null,
          "exchange_long": null,
          "country": "in",
          "type": "equity",
          "industry": "Basic Materials",
          "match_score": 26.471325,
          "sentiment_score": 0.6482,
          "highlights": [
            {
              "highlight": "Tejas Networks, Inox Wind, <em>Welspun</[+288 characters]",
              "sentiment": 0.6482,
              "highlighted_in": "main_text"
            }
          ]
        },
        {
          "symbol": "INOXWIND.BO",
          "name": "Inox Wind Limited",
          "exchange": null,
          "exchange_long": null,
          "country": "in",
          "type": "equity",
          "industry": "Industrials",
          "match_score": 25.264704,
          "sentiment_score": 0.6482,
          "highlights": [
            {
              "highlight": "Tejas Networks, <em>Inox</em> <em>Wind</[+288 characters]",
              "sentiment": 0.6482,
              "highlighted_in": "main_text"
            }
          ]
        },
        {
          "symbol": "SWANENERGY.BO",
          "name": "Swan Energy Limited",
          "exchange": null,
          "exchange_long": null,
          "country": "in",
          "type": "equity",
          "industry": "Consumer Cyclical",
          "match_score": 22.57184,
          "sentiment_score": 0.6289,
          "highlights": [
            {
              "highlight": "CAMS, <em>Swan</em> <em>Energy</em>, PGE[+316 characters]",
              "sentiment": 0.6289,
              "highlighted_in": "main_text"
            }
          ]
        },
        {
          "symbol": "TATAELXSI.BO",
          "name": "Tata Elxsi Limited",
          "exchange": null,
          "exchange_long": null,
          "country": "in",
          "type": "equity",
          "industry": "Technology",
          "match_score": 28.319164,
          "sentiment_score": 0,
          "highlights": [
            {
              "highlight": "Midcap & smallcap movers\n\nIn the midcap [+261 characters]",
              "sentiment": 0,
              "highlighted_in": "main_text"
            }
          ]
        },
        {
          "symbol": "NATCOPHARM.BO",
          "name": "NATCO Pharma Limited",
          "exchange": null,
          "exchange_long": null,
          "country": "in",
          "type": "equity",
          "industry": "Healthcare",
          "match_score": 28.483727,
          "sentiment_score": 0.7378,
          "highlights": [
            {
              "highlight": "CAMS, Swan Energy, PGEL, <em>Natco</em> [+316 characters]",
              "sentiment": 0.7378,
              "highlighted_in": "main_text"
            }
          ]
        },
        {
          "symbol": "FORCEMOT.BO",
          "name": "Force Motors Limited",
          "exchange": null,
          "exchange_long": null,
          "country": "in",
          "type": "equity",
          "industry": "Consumer Cyclical",
          "match_score": 20.97092,
          "sentiment_score": -0.296,
          "highlights": [
            {
              "highlight": "CEAT, Gillette, <em>Force</em> <em>Motor[+279 characters]",
              "sentiment": -0.296,
              "highlighted_in": "main_text"
            }
          ]
        },
        {
          "symbol": "CARTRADE.BO",
          "name": "CarTrade Tech Limited",
          "exchange": null,
          "exchange_long": null,
          "country": "in",
          "type": "equity",
          "industry": "N/A",
          "match_score": 26.64604,
          "sentiment_score": 0.6482,
          "highlights": [
            {
              "highlight": "On the BSE, Waaree Renewable, STL Tech, [+188 characters]",
              "sentiment": 0.6482,
              "highlighted_in": "main_text"
            }
          ]
        }
      ],
      "similar": []
    }
  ]
}